wetest/osplatform/__init__.py
wetest/osplatform/conn.py
wetest_osplatform-0.0.3.dist-info/METADATA
wetest_osplatform-0.0.3.dist-info/WHEEL
wetest_osplatform-0.0.3.dist-info/top_level.txt
wetest_osplatform-0.0.3.dist-info/RECORD
