Metadata-Version: 2.4
Name: wetest-osplatform
Version: 0.0.3
Author: Tencent WeTest
Author-email: WeTest@wetest.net
Requires-Python: >=3.7
Requires-Dist: adbutils
Requires-Dist: tidevice
Dynamic: author
Dynamic: author-email
Dynamic: description
Dynamic: description-content-type
Dynamic: requires-dist
Dynamic: requires-python
